rollcred/__init__.py
rollcred/main.py
rollcred-0.0.6.dist-info/WHEEL
rollcred-0.0.6.dist-info/METADATA
rollcred-0.0.6.dist-info/RECORD
