Metadata-Version: 2.1
Name: rollcred
Version: 0.0.6
Summary: 
Author: trejas
Author-email: 4763901+trejas@users.noreply.github.com
Requires-Python: >=3.9,<4.0
Classifier: Programming Language :: Python :: 3
Classifier: Programming Language :: Python :: 3.9
Classifier: Programming Language :: Python :: 3.10
Requires-Dist: click (==7.1.2)
Requires-Dist: pyperclip (==1.8.2)
